{
  "minecraft:recipes/decorations/item_frame": {
    "criteria": {
      "has_leather": "2024-12-24 06:23:38 +0000"
    },
    "done": true
  },
  "minecraft:recipes/combat/leather_chestplate": {
    "criteria": {
      "has_leather": "2024-12-24 06:23:38 +0000"
    },
    "done": true
  },
  "tombstone:tutorial/root": {
    "criteria": {
      "auto": "2024-12-24 06:22:39 +0000"
    },
    "done": true
  },
  "minecraft:recipes/transportation/dark_oak_boat": {
    "criteria": {
      "entered_water": "2024-12-24 05:12:55 +0000"
    },
    "done": true
  },
  "tombstone:tutorial/christmas": {
    "criteria": {
      "coded_trigger": "2024-12-24 06:22:39 +0000"
    },
    "done": true
  },
  "minecraft:husbandry/root": {
    "criteria": {
      "consumed_item": "2024-12-24 06:24:32 +0000"
    },
    "done": true
  },
  "minecraft:recipes/transportation/birch_boat": {
    "criteria": {
      "entered_water": "2024-12-24 05:12:55 +0000"
    },
    "done": true
  },
  "minecraft:recipes/transportation/acacia_boat": {
    "criteria": {
      "entered_water": "2024-12-24 05:12:55 +0000"
    },
    "done": true
  },
  "minecraft:husbandry/balanced_diet": {
    "criteria": {
      "beef": "2024-12-24 06:24:32 +0000"
    },
    "done": false
  },
  "minecraft:adventure/root": {
    "criteria": {
      "killed_something": "2024-12-24 06:23:36 +0000"
    },
    "done": true
  },
  "minecraft:recipes/transportation/boat": {
    "criteria": {
      "entered_water": "2024-12-24 05:12:55 +0000"
    },
    "done": true
  },
  "minecraft:recipes/combat/leather_boots": {
    "criteria": {
      "has_leather": "2024-12-24 06:23:38 +0000"
    },
    "done": true
  },
  "minecraft:recipes/transportation/jungle_boat": {
    "criteria": {
      "entered_water": "2024-12-24 05:12:55 +0000"
    },
    "done": true
  },
  "minecraft:recipes/transportation/spruce_boat": {
    "criteria": {
      "entered_water": "2024-12-24 05:12:55 +0000"
    },
    "done": true
  },
  "minecraft:recipes/combat/leather_helmet": {
    "criteria": {
      "has_leather": "2024-12-24 06:23:38 +0000"
    },
    "done": true
  },
  "minecraft:adventure/adventuring_time": {
    "criteria": {
      "forest": "2024-12-24 06:24:50 +0000",
      "swampland": "2024-12-24 05:13:16 +0000",
      "deep_ocean": "2024-12-24 05:12:55 +0000",
      "plains": "2024-12-24 05:13:21 +0000"
    },
    "done": false
  },
  "minecraft:recipes/combat/leather_leggings": {
    "criteria": {
      "has_leather": "2024-12-24 06:23:38 +0000"
    },
    "done": true
  }
}